twgw/__init__.py
twgw/twgw.py
twgw-0.5.5.dist-info/LICENSE
twgw-0.5.5.dist-info/METADATA
twgw-0.5.5.dist-info/WHEEL
twgw-0.5.5.dist-info/top_level.txt
twgw-0.5.5.dist-info/RECORD
