Metadata-Version: 2.1
Name: twgw
Version: 0.5.5
Summary: TWGW
Author: Iyappan
Author-email: iyappan@trackerwave.com
Keywords: twgw
Classifier: Development Status :: 1 - Planning
Classifier: Intended Audience :: Developers
Classifier: Programming Language :: Python :: 3
Classifier: Operating System :: Unix
Classifier: Operating System :: MacOS :: MacOS X
Classifier: Operating System :: Microsoft :: Windows
License-File: LICENSE
Requires-Dist: cryptography
Requires-Dist: requests
Requires-Dist: pytz
Requires-Dist: paho-mqtt
Requires-Dist: psutil
